pdbcolor/__init__.py
pdbcolor/__main__.py
pdbcolor-0.4.2.dist-info/METADATA
pdbcolor-0.4.2.dist-info/WHEEL
pdbcolor-0.4.2.dist-info/licenses/LICENSE
pdbcolor-0.4.2.dist-info/RECORD
