Metadata-Version: 2.4
Name: pdbcolor
Version: 0.4.2
Summary: A simple package to add code highlighting to the python debugger (PDB).
Project-URL: Homepage, https://github.com/Alex-JG3/pdbcolor
Project-URL: Issues, https://github.com/Alex-JG3/pdbcolor/issues
Author: Alex Gregory
License-Expression: MIT
License-File: LICENSE
Classifier: Operating System :: OS Independent
Classifier: Programming Language :: Python :: 3
Requires-Python: >=3.9
Requires-Dist: pygments
Provides-Extra: dev
Requires-Dist: pre-commit; extra == 'dev'
Requires-Dist: ruff; extra == 'dev'
